signupto
