Metadata-Version: 1.1
Name: signupto
Version: 0.1
Summary: sign-up.to API client
Home-page: https://bitbucket.org/spookylukey/signupto
Author: Luke Plant
Author-email: L.Plant.98@cantab.net
License: BSD
Keywords: signupto
Platform: UNKNOWN
Classifier: Development Status :: 3 - Alpha
Classifier: Intended Audience :: Developers
Classifier: License :: OSI Approved :: BSD License
Classifier: Natural Language :: English
Classifier: Programming Language :: Python :: 2
Classifier: Programming Language :: Python :: 2.7
Classifier: Programming Language :: Python :: 3
Classifier: Programming Language :: Python :: 3.3
